LICENSE
MANIFEST.in
README.md
setup.py
scup/__init__.py
scup/auth.py
scup/bind.py
scup/exceptions.py
scup/scup_api.py
scup_python.egg-info/PKG-INFO
scup_python.egg-info/SOURCES.txt
scup_python.egg-info/dependency_links.txt
scup_python.egg-info/requires.txt
scup_python.egg-info/top_level.txt