Metadata-Version: 1.1
Name: scup-python
Version: 0.1.3
Summary: Unnofficial Python library for the Scup API v1.1. http://www.scup.com/docs/api
Home-page: https://github.com/gdmachado/scup-python
Author: Gustavo Machado
Author-email: gdmachado@me.com
License: UNKNOWN
Platform: UNKNOWN
Classifier: Development Status :: 2 - Pre-Alpha
Classifier: Intended Audience :: Developers
Classifier: Programming Language :: Python
Classifier: Natural Language :: English
Classifier: License :: OSI Approved :: Apache Software License
Classifier: Programming Language :: Python :: 2.6
Classifier: Programming Language :: Python :: 2.7
Classifier: Topic :: Software Development :: Libraries
Classifier: Operating System :: OS Independent
